fastapi_crudbuilder/__init__.py
fastapi_crudbuilder/builder.py
fastapi_crudbuilder/generators.py
fastapi_crudbuilder/transform.py
fastapi_crudbuilder-0.2.5.dist-info/LICENSE
fastapi_crudbuilder-0.2.5.dist-info/METADATA
fastapi_crudbuilder-0.2.5.dist-info/WHEEL
fastapi_crudbuilder-0.2.5.dist-info/RECORD
