Metadata-Version: 2.1
Name: fastapi_crudbuilder
Version: 0.2.5
Summary: CRUDBuilder helps you to create CRUD endpoints for your FastAPI/ SqlAlchemy database models.
Home-page: https://github.com/TetricusLabs/fastapi_crudbuilder
License: MIT
Keywords: FastAPI,CRUD,SQLAlchemy
Author: Tetricus Labs Team
Author-email: support@tetricuslabs.com
Requires-Python: >=3.10,<4.0
Classifier: Development Status :: 3 - Alpha
Classifier: Framework :: FastAPI
Classifier: Intended Audience :: Developers
Classifier: License :: OSI Approved :: MIT License
Classifier: Programming Language :: Python :: 3
Classifier: Programming Language :: Python :: 3.10
Classifier: Programming Language :: Python :: 3.11
Classifier: Programming Language :: Python :: 3.12
Requires-Dist: fastapi (>=0.111.0,<0.112.0)
Requires-Dist: sqlalchemy (>=2.0.31,<3.0.0)
Project-URL: Repository, https://github.com/TetricusLabs/fastapi_crudbuilder
